cli/__init__.py
cli/main.py
cli/commands/__init__.py
cli/commands/create.py
cli/commands/hooks.py
cli/commands/init.py
cli/commands/render.py
cli/commands/test.py
llmhq_promptops/__init__.py
llmhq_promptops/prompt_manager.py
llmhq_promptops/core/__init__.py
llmhq_promptops/core/git_versioning.py
llmhq_promptops/core/template.py
llmhq_promptops/core/version_detector.py
llmhq_promptops/hooks/__init__.py
llmhq_promptops/hooks/post_commit.py
llmhq_promptops/hooks/pre_commit.py
llmhq_promptops/utils/__init__.py
llmhq_promptops-0.1.1.dist-info/licenses/LICENSE
llmhq_promptops-0.1.1.dist-info/METADATA
llmhq_promptops-0.1.1.dist-info/WHEEL
llmhq_promptops-0.1.1.dist-info/entry_points.txt
llmhq_promptops-0.1.1.dist-info/top_level.txt
llmhq_promptops-0.1.1.dist-info/RECORD
