Metadata-Version: 2.4
Name: llmhq-promptops
Version: 0.1.1
Summary: Comprehensive prompt management and testing framework for production LLM workflows with automated git versioning
Author-email: jision <jisionpc@gmail.com>
Maintainer-email: jision <jisionpc@gmail.com>
License: MIT
Project-URL: Homepage, https://github.com/llmhq-hub/promptops
Project-URL: Documentation, https://github.com/llmhq-hub/promptops
Project-URL: Repository, https://github.com/llmhq-hub/promptops
Project-URL: Issues, https://github.com/llmhq-hub/promptops/issues
Project-URL: Changelog, https://github.com/llmhq-hub/promptops/blob/main/CHANGELOG.md
Keywords: llm,prompt,versioning,testing,git,automation,cli,sdk,production,workflow,template,jinja2
Classifier: Development Status :: 4 - Beta
Classifier: Intended Audience :: Developers
Classifier: License :: OSI Approved :: MIT License
Classifier: Operating System :: OS Independent
Classifier: Programming Language :: Python :: 3
Classifier: Programming Language :: Python :: 3.8
Classifier: Programming Language :: Python :: 3.9
Classifier: Programming Language :: Python :: 3.10
Classifier: Programming Language :: Python :: 3.11
Classifier: Programming Language :: Python :: 3.12
Classifier: Topic :: Software Development :: Libraries :: Python Modules
Classifier: Topic :: Scientific/Engineering :: Artificial Intelligence
Classifier: Topic :: Software Development :: Version Control :: Git
Classifier: Topic :: Software Development :: Testing
Classifier: Topic :: Text Processing :: Linguistic
Requires-Python: >=3.8
License-File: LICENSE
Requires-Dist: click>=8.1.8
Requires-Dist: Jinja2>=3.1.6
Requires-Dist: PyYAML>=6.0.2
Requires-Dist: typer>=0.15.2
Requires-Dist: GitPython>=3.1.0
Requires-Dist: typing_extensions>=4.13.1
Provides-Extra: dev
Requires-Dist: pytest>=7.0.0; extra == "dev"
Requires-Dist: black>=22.0.0; extra == "dev"
Requires-Dist: flake8>=4.0.0; extra == "dev"
Requires-Dist: mypy>=1.0.0; extra == "dev"
Requires-Dist: pre-commit>=3.0.0; extra == "dev"
Dynamic: license-file
